pylsprotocol/__init__.py
pylsprotocol/lsprotocol.py
pylsprotocol-0.1.4.dist-info/METADATA
pylsprotocol-0.1.4.dist-info/WHEEL
pylsprotocol-0.1.4.dist-info/top_level.txt
pylsprotocol-0.1.4.dist-info/RECORD
